advantage_air/__init__.py
advantage_air-0.4.4.dist-info/LICENSE
advantage_air-0.4.4.dist-info/METADATA
advantage_air-0.4.4.dist-info/WHEEL
advantage_air-0.4.4.dist-info/top_level.txt
advantage_air-0.4.4.dist-info/RECORD
