Metadata-Version: 2.1
Name: advantage_air
Version: 0.4.4
Summary: API helper for Advantage Air's MyAir and e-zone API
Home-page: https://github.com/Bre77/advantage_air
Author: Brett Adams
Author-email: brett@ba.id.au
Classifier: Programming Language :: Python :: 3
Classifier: License :: OSI Approved :: MIT License
Classifier: Operating System :: OS Independent
Requires-Python: >=3.6
License-File: LICENSE
